{
  "stories": [
    {
      "title": "Naruto",
      "author": "Masashi Kishimoto",
      "image": "https://image.com/naruto.jpg",
      "description": "Truyện ninja nổi tiếng"
    }
  ],
  "categories": [
    {
      "title": "vvvv",
      "description ": "okee",
      "id": 7
    },
    {
      "title": "fffff",
      "description": "okkkk",
      "date": "12/03/2026",
      "isActive": true,
      "id": 10
    },
    {
      "title": "Vượng ",
      "description": "bóng đá thể thao",
      "date": "01/12/2006",
      "isActive": true,
      "id": 11
    }
  ],
  "users": []
}